LegacyVersion/LegacyCode.py
LegacyVersion/__init__.py
LegacyVersion-1.0.1.dist-info/LICENSE
LegacyVersion-1.0.1.dist-info/METADATA
LegacyVersion-1.0.1.dist-info/WHEEL
LegacyVersion-1.0.1.dist-info/top_level.txt
LegacyVersion-1.0.1.dist-info/RECORD
