Metadata-Version: 2.1
Name: LegacyVersion
Version: 1.0.1
Summary: Versioning library for Python 3.11+
Author: Stanislav Jochman
Author-email: <s.jochman@gmail.com>
Keywords: python,LegacyVersion,_BaseVersion
Classifier: Development Status :: 5 - Production/Stable
Classifier: Intended Audience :: Developers
Classifier: Programming Language :: Python :: 3
Classifier: Operating System :: Unix
Classifier: Operating System :: MacOS :: MacOS X
Classifier: Operating System :: Microsoft :: Windows
License-File: LICENSE
